djangorestframework_hstore-1.3.dist-info/METADATA
djangorestframework_hstore-1.3.dist-info/RECORD
djangorestframework_hstore-1.3.dist-info/DESCRIPTION.rst
djangorestframework_hstore-1.3.dist-info/top_level.txt
djangorestframework_hstore-1.3.dist-info/WHEEL
djangorestframework_hstore-1.3.dist-info/metadata.json
rest_framework_hstore/__init__.py
rest_framework_hstore/models.py
rest_framework_hstore/serializers.py
rest_framework_hstore/fields.py
