Metadata-Version: 1.1
Name: djangorestframework-hstore
Version: 1.3
Summary: Django Rest Framework tools for django-hstore
Home-page: https://github.com/djangonauts/django-rest-framework-hstore
Author: Federico Capoano
Author-email: django-rest-framework-hstore@googlegroups.com
License: BSD
Download-URL: https://github.com/djangonauts/django-rest-framework-hstore/releases
Platform: Platform Indipendent
Classifier: Development Status :: 4 - Beta
Classifier: Environment :: Web Environment
Classifier: Intended Audience :: Developers
Classifier: License :: OSI Approved :: BSD License
Classifier: Operating System :: OS Independent
Classifier: Programming Language :: Python
Classifier: Topic :: Internet :: WWW/HTTP :: Dynamic Content
Classifier: Framework :: Django
Classifier: Programming Language :: Python
Classifier: Programming Language :: Python :: 2
Classifier: Programming Language :: Python :: 2.7
Classifier: Programming Language :: Python :: 3
Classifier: Programming Language :: Python :: 3.4
